scd30_exporter/__init__.py
scd30_exporter/cli.py
scd30_exporter/py.typed
scd30_exporter-0.2.0.dist-info/entry_points.txt
scd30_exporter-0.2.0.dist-info/LICENSE
scd30_exporter-0.2.0.dist-info/WHEEL
scd30_exporter-0.2.0.dist-info/METADATA
scd30_exporter-0.2.0.dist-info/RECORD
