Metadata-Version: 2.1
Name: scd30-exporter
Version: 0.2.0
Summary: Prometheus exporter for Adafruit SCD-30 - NDIR CO2 Temperature and Humidity Sensor
Home-page: https://github.com/node13h/scd30-exporter
License: MIT
Author: Sergej Alikov
Author-email: sergej@alikov.com
Requires-Python: >=3.9,<4.0
Classifier: License :: OSI Approved :: MIT License
Classifier: Programming Language :: Python :: 3
Classifier: Programming Language :: Python :: 3.10
Classifier: Programming Language :: Python :: 3.9
Requires-Dist: adafruit-circuitpython-scd30 (>=2.2.9,<3.0.0)
Requires-Dist: prometheus-client (>=0.16.0,<0.17.0)
Project-URL: Repository, https://github.com/node13h/scd30-exporter
